FQ/__init__.py
FQ/auto_install.py
fq1-1.0.dist-info/METADATA
fq1-1.0.dist-info/WHEEL
fq1-1.0.dist-info/entry_points.txt
fq1-1.0.dist-info/top_level.txt
fq1-1.0.dist-info/RECORD
