Metadata-Version: 2.4
Name: fq1
Version: 1.0
Summary: Thư viện tự động tải về GitHub repo
Home-page: https://github.com/NgocAnLam/fqtest.git
Author: NgocAn
Author-email: anlam9614@gmail.com
Classifier: Programming Language :: Python :: 3
Classifier: License :: OSI Approved :: MIT License
Classifier: Operating System :: OS Independent
Requires-Python: >=3.6
Dynamic: author
Dynamic: author-email
Dynamic: classifier
Dynamic: home-page
Dynamic: requires-python
Dynamic: summary
